pandas_sphinx/__init__.py
pandas_sphinx/constants.py
pandas_sphinx/version.py
pandas_sphinx-0.1.1.dist-info/METADATA
pandas_sphinx-0.1.1.dist-info/WHEEL
pandas_sphinx-0.1.1.dist-info/licenses/LICENSE
pandas_sphinx-0.1.1.dist-info/RECORD
