Metadata-Version: 2.1
Name: pandas-sphinx
Version: 0.1.1
Summary: Render a pandas DataFrame as an opinionated table for Sphinx.
Project-URL: Documentation, https://github.com/joaopalmeiro/pandas-sphinx#readme
Project-URL: Issues, https://github.com/joaopalmeiro/pandas-sphinx/issues
Project-URL: Source, https://github.com/joaopalmeiro/pandas-sphinx
Author-email: João Palmeiro <jm.palmeiro@campus.fct.unl.pt>
License-File: LICENSE
Classifier: Development Status :: 4 - Beta
Classifier: Intended Audience :: Developers
Classifier: Intended Audience :: Science/Research
Classifier: License :: OSI Approved :: MIT License
Classifier: Operating System :: OS Independent
Classifier: Programming Language :: Python
Classifier: Programming Language :: Python :: 3
Classifier: Programming Language :: Python :: 3 :: Only
Classifier: Programming Language :: Python :: 3.7
Classifier: Programming Language :: Python :: 3.8
Classifier: Programming Language :: Python :: 3.9
Classifier: Programming Language :: Python :: 3.10
Classifier: Programming Language :: Python :: 3.11
Requires-Python: >=3.7
Requires-Dist: pandas>=1.3.4
Requires-Dist: tabulate
